pysplot/__init__.py
pysplot/io/__init__.py
pysplot/io/data.py
pysplot/io/data_helpers.py
pysplot/plots/__init__.py
pysplot/plots/plottypes.py
pysplot/tests/__init__.py
pysplot/util/__init__.py
pysplot/util/chmaps.py
pysplot-0.1.0.dist-info/licenses/LICENSE
pysplot-0.1.0.dist-info/METADATA
pysplot-0.1.0.dist-info/WHEEL
pysplot-0.1.0.dist-info/top_level.txt
pysplot-0.1.0.dist-info/RECORD
