Metadata-Version: 2.4
Name: pysplot
Version: 0.1.0
Summary: A spatial and temporal plotting package for heliophysics data
Home-page: https://github.com/pysplot/pysplot
Author: Brent Smith
Author-email: brent.smith@jhuapl.edu
Classifier: Programming Language :: Python :: 3
Classifier: License :: OSI Approved :: MIT License
Classifier: Operating System :: OS Independent
Requires-Python: >=3.9
License-File: LICENSE
Requires-Dist: sunpy>=5.1.5
Requires-Dist: pandas>=2.2.3
Requires-Dist: matplotlib>=3.9.0
Provides-Extra: whpi
Requires-Dist: imageio>=2.9.0; extra == "whpi"
Provides-Extra: examples
Requires-Dist: cdasws>=1.7.42; extra == "examples"
Requires-Dist: cdflib>=0.4.9; extra == "examples"
Requires-Dist: xarray>=0.20.1; extra == "examples"
Provides-Extra: test
Requires-Dist: pytest; extra == "test"
Dynamic: author
Dynamic: author-email
Dynamic: classifier
Dynamic: description
Dynamic: description-content-type
Dynamic: home-page
Dynamic: license-file
Dynamic: provides-extra
Dynamic: requires-dist
Dynamic: requires-python
Dynamic: summary
